figgiebot/__init__.py
figgiebot/figgiebot.py
figgiebot-1.0.1.dist-info/METADATA
figgiebot-1.0.1.dist-info/WHEEL
figgiebot-1.0.1.dist-info/top_level.txt
figgiebot-1.0.1.dist-info/RECORD
