Metadata-Version: 2.1
Name: figgiebot
Version: 1.0.1
Summary: Create bots to play the card game Figgie at https://figgie.com/
Author: CodingYuno
Project-URL: Source Code, https://github.com/CodingYuno/figgiebot
Project-URL: Issue Tracker, https://github.com/CodingYuno/figgiebot/issues/
Classifier: Intended Audience :: Developers
Classifier: License :: OSI Approved :: MIT License
Classifier: Operating System :: OS Independent
Classifier: Programming Language :: Python :: 3
Classifier: Topic :: Software Development :: Libraries :: Application Frameworks
Requires-Python: >=3.8
Requires-Dist: beautifulsoup4 (>=4.9.3)
Requires-Dist: selenium (>=4.7.2)
